[
    {
        "type": "message",
        "subtype": "file_share",
        "text": "<@U02F8LF2X|chewbacca> uploaded a file: <https:\/\/uncorked.slack.com\/files\/chewbacca\/F0A6U2T8A\/screen_shot_2015-09-04_at_3.54.58_pm.png|Screen Shot 2015-09-04 at 3.54.58 PM.png>",
        "file": {
            "id": "F0A6U2T8A",
            "created": 1441407318,
            "timestamp": 1441407318,
            "name": "Screen Shot 2015-09-04 at 3.54.58 PM.png",
            "title": "Screen Shot 2015-09-04 at 3.54.58 PM.png",
            "mimetype": "image\/png",
            "filetype": "png",
            "pretty_type": "PNG",
            "user": "U02F8LF2X",
            "editable": false,
            "size": 359823,
            "mode": "hosted",
            "is_external": false,
            "external_type": "",
            "is_public": true,
            "public_url_shared": false,
            "display_as_bot": false,
            "username": "",
            "url_private": "https:\/\/files.slack.com\/files-pri\/T0260V1BR-F0A6U2T8A\/screen_shot_2015-09-04_at_3.54.58_pm.png?t=xoxe-2204987399-220009572576-220663233794-4d92389b8a",
            "url_private_download": "https:\/\/files.slack.com\/files-pri\/T0260V1BR-F0A6U2T8A\/download\/screen_shot_2015-09-04_at_3.54.58_pm.png?t=xoxe-2204987399-220009572576-220663233794-4d92389b8a",
            "thumb_64": "https:\/\/files.slack.com\/files-tmb\/T0260V1BR-F0A6U2T8A-f2fc415cfb\/screen_shot_2015-09-04_at_3.54.58_pm_64.png?t=xoxe-2204987399-220009572576-220663233794-4d92389b8a",
            "thumb_80": "https:\/\/files.slack.com\/files-tmb\/T0260V1BR-F0A6U2T8A-f2fc415cfb\/screen_shot_2015-09-04_at_3.54.58_pm_80.png?t=xoxe-2204987399-220009572576-220663233794-4d92389b8a",
            "thumb_360": "https:\/\/files.slack.com\/files-tmb\/T0260V1BR-F0A6U2T8A-f2fc415cfb\/screen_shot_2015-09-04_at_3.54.58_pm_360.png?t=xoxe-2204987399-220009572576-220663233794-4d92389b8a",
            "thumb_360_w": 360,
            "thumb_360_h": 267,
            "thumb_480": "https:\/\/files.slack.com\/files-tmb\/T0260V1BR-F0A6U2T8A-f2fc415cfb\/screen_shot_2015-09-04_at_3.54.58_pm_480.png?t=xoxe-2204987399-220009572576-220663233794-4d92389b8a",
            "thumb_480_w": 480,
            "thumb_480_h": 356,
            "thumb_160": "https:\/\/files.slack.com\/files-tmb\/T0260V1BR-F0A6U2T8A-f2fc415cfb\/screen_shot_2015-09-04_at_3.54.58_pm_160.png?t=xoxe-2204987399-220009572576-220663233794-4d92389b8a",
            "thumb_720": "https:\/\/files.slack.com\/files-tmb\/T0260V1BR-F0A6U2T8A-f2fc415cfb\/screen_shot_2015-09-04_at_3.54.58_pm_720.png?t=xoxe-2204987399-220009572576-220663233794-4d92389b8a",
            "thumb_720_w": 720,
            "thumb_720_h": 534,
            "image_exif_rotation": 1,
            "original_w": 802,
            "original_h": 595,
            "permalink": "https:\/\/uncorked.slack.com\/files\/chewbacca\/F0A6U2T8A\/screen_shot_2015-09-04_at_3.54.58_pm.png",
            "permalink_public": "https:\/\/slack-files.com\/T0260V1BR-F0A6U2T8A-51e0d09595",
            "channels": [
                "C02LNQWC9"
            ],
            "groups": [],
            "ims": [],
            "comments_count": 0
        },
        "user": "U02F8LF2X",
        "upload": true,
        "display_as_bot": false,
        "username": "chewbacca",
        "bot_id": null,
        "ts": "1441407320.000002"
    },
    {
        "type": "message",
        "subtype": "file_share",
        "text": "<@U02F8LF2X|chewbacca> uploaded a file: <https:\/\/uncorked.slack.com\/files\/chewbacca\/F0A6TNB0U\/screen_shot_2015-09-04_at_3.54.38_pm.png|Screen Shot 2015-09-04 at 3.54.38 PM.png>",
        "file": {
            "id": "F0A6TNB0U",
            "created": 1441407334,
            "timestamp": 1441407334,
            "name": "Screen Shot 2015-09-04 at 3.54.38 PM.png",
            "title": "Screen Shot 2015-09-04 at 3.54.38 PM.png",
            "mimetype": "image\/png",
            "filetype": "png",
            "pretty_type": "PNG",
            "user": "U02F8LF2X",
            "editable": false,
            "size": 527992,
            "mode": "hosted",
            "is_external": false,
            "external_type": "",
            "is_public": true,
            "public_url_shared": false,
            "display_as_bot": false,
            "username": "",
            "url_private": "https:\/\/files.slack.com\/files-pri\/T0260V1BR-F0A6TNB0U\/screen_shot_2015-09-04_at_3.54.38_pm.png?t=xoxe-2204987399-220009572576-220663233794-4d92389b8a",
            "url_private_download": "https:\/\/files.slack.com\/files-pri\/T0260V1BR-F0A6TNB0U\/download\/screen_shot_2015-09-04_at_3.54.38_pm.png?t=xoxe-2204987399-220009572576-220663233794-4d92389b8a",
            "thumb_64": "https:\/\/files.slack.com\/files-tmb\/T0260V1BR-F0A6TNB0U-dad96c88a9\/screen_shot_2015-09-04_at_3.54.38_pm_64.png?t=xoxe-2204987399-220009572576-220663233794-4d92389b8a",
            "thumb_80": "https:\/\/files.slack.com\/files-tmb\/T0260V1BR-F0A6TNB0U-dad96c88a9\/screen_shot_2015-09-04_at_3.54.38_pm_80.png?t=xoxe-2204987399-220009572576-220663233794-4d92389b8a",
            "thumb_360": "https:\/\/files.slack.com\/files-tmb\/T0260V1BR-F0A6TNB0U-dad96c88a9\/screen_shot_2015-09-04_at_3.54.38_pm_360.png?t=xoxe-2204987399-220009572576-220663233794-4d92389b8a",
            "thumb_360_w": 360,
            "thumb_360_h": 302,
            "thumb_480": "https:\/\/files.slack.com\/files-tmb\/T0260V1BR-F0A6TNB0U-dad96c88a9\/screen_shot_2015-09-04_at_3.54.38_pm_480.png?t=xoxe-2204987399-220009572576-220663233794-4d92389b8a",
            "thumb_480_w": 480,
            "thumb_480_h": 403,
            "thumb_160": "https:\/\/files.slack.com\/files-tmb\/T0260V1BR-F0A6TNB0U-dad96c88a9\/screen_shot_2015-09-04_at_3.54.38_pm_160.png?t=xoxe-2204987399-220009572576-220663233794-4d92389b8a",
            "thumb_720": "https:\/\/files.slack.com\/files-tmb\/T0260V1BR-F0A6TNB0U-dad96c88a9\/screen_shot_2015-09-04_at_3.54.38_pm_720.png?t=xoxe-2204987399-220009572576-220663233794-4d92389b8a",
            "thumb_720_w": 720,
            "thumb_720_h": 604,
            "image_exif_rotation": 1,
            "original_w": 878,
            "original_h": 737,
            "permalink": "https:\/\/uncorked.slack.com\/files\/chewbacca\/F0A6TNB0U\/screen_shot_2015-09-04_at_3.54.38_pm.png",
            "permalink_public": "https:\/\/slack-files.com\/T0260V1BR-F0A6TNB0U-59ff761155",
            "channels": [
                "C02LNQWC9"
            ],
            "groups": [],
            "ims": [],
            "comments_count": 0
        },
        "user": "U02F8LF2X",
        "upload": true,
        "display_as_bot": false,
        "username": "chewbacca",
        "bot_id": null,
        "ts": "1441407336.000003"
    },
    {
        "type": "message",
        "user": "U02F8LF2X",
        "text": "(it's the miter saw)",
        "ts": "1441407410.000004"
    },
    {
        "type": "message",
        "subtype": "file_share",
        "text": "<@U02F8LF2X|chewbacca> uploaded a file: <https:\/\/uncorked.slack.com\/files\/chewbacca\/F0A6UL8E8\/kat.mov|kat.mov>",
        "file": {
            "id": "F0A6UL8E8",
            "created": 1441409179,
            "timestamp": 1441409179,
            "name": "kat.mov",
            "title": "kat.mov",
            "mimetype": "video\/quicktime",
            "filetype": "mov",
            "pretty_type": "QuickTime Movie",
            "user": "U02F8LF2X",
            "editable": false,
            "size": 2018650,
            "mode": "hosted",
            "is_external": false,
            "external_type": "",
            "is_public": true,
            "public_url_shared": false,
            "display_as_bot": false,
            "username": "",
            "url_private": "https:\/\/files.slack.com\/files-pri\/T0260V1BR-F0A6UL8E8\/kat.mov?t=xoxe-2204987399-220009572576-220663233794-4d92389b8a",
            "url_private_download": "https:\/\/files.slack.com\/files-pri\/T0260V1BR-F0A6UL8E8\/download\/kat.mov?t=xoxe-2204987399-220009572576-220663233794-4d92389b8a",
            "permalink": "https:\/\/uncorked.slack.com\/files\/chewbacca\/F0A6UL8E8\/kat.mov",
            "permalink_public": "https:\/\/slack-files.com\/T0260V1BR-F0A6UL8E8-f9216d54ec",
            "channels": [
                "C02LNQWC9"
            ],
            "groups": [],
            "ims": [],
            "comments_count": 0
        },
        "user": "U02F8LF2X",
        "upload": true,
        "display_as_bot": false,
        "username": "chewbacca",
        "bot_id": null,
        "ts": "1441409180.000005"
    },
    {
        "type": "message",
        "user": "U02F8LF2X",
        "text": "(it's the kat)",
        "ts": "1441409193.000006"
    },
    {
        "type": "message",
        "subtype": "file_share",
        "text": "<@U02F8LF2X|chewbacca> uploaded a file: <https:\/\/uncorked.slack.com\/files\/chewbacca\/F0A6V0N9F\/screen_shot_2015-09-04_at_4.26.59_pm.png|Screen Shot 2015-09-04 at 4.26.59 PM.png>",
        "file": {
            "id": "F0A6V0N9F",
            "created": 1441409231,
            "timestamp": 1441409231,
            "name": "Screen Shot 2015-09-04 at 4.26.59 PM.png",
            "title": "Screen Shot 2015-09-04 at 4.26.59 PM.png",
            "mimetype": "image\/png",
            "filetype": "png",
            "pretty_type": "PNG",
            "user": "U02F8LF2X",
            "editable": false,
            "size": 234646,
            "mode": "hosted",
            "is_external": false,
            "external_type": "",
            "is_public": true,
            "public_url_shared": false,
            "display_as_bot": false,
            "username": "",
            "url_private": "https:\/\/files.slack.com\/files-pri\/T0260V1BR-F0A6V0N9F\/screen_shot_2015-09-04_at_4.26.59_pm.png?t=xoxe-2204987399-220009572576-220663233794-4d92389b8a",
            "url_private_download": "https:\/\/files.slack.com\/files-pri\/T0260V1BR-F0A6V0N9F\/download\/screen_shot_2015-09-04_at_4.26.59_pm.png?t=xoxe-2204987399-220009572576-220663233794-4d92389b8a",
            "thumb_64": "https:\/\/files.slack.com\/files-tmb\/T0260V1BR-F0A6V0N9F-2793332b36\/screen_shot_2015-09-04_at_4.26.59_pm_64.png?t=xoxe-2204987399-220009572576-220663233794-4d92389b8a",
            "thumb_80": "https:\/\/files.slack.com\/files-tmb\/T0260V1BR-F0A6V0N9F-2793332b36\/screen_shot_2015-09-04_at_4.26.59_pm_80.png?t=xoxe-2204987399-220009572576-220663233794-4d92389b8a",
            "thumb_360": "https:\/\/files.slack.com\/files-tmb\/T0260V1BR-F0A6V0N9F-2793332b36\/screen_shot_2015-09-04_at_4.26.59_pm_360.png?t=xoxe-2204987399-220009572576-220663233794-4d92389b8a",
            "thumb_360_w": 336,
            "thumb_360_h": 360,
            "thumb_480": "https:\/\/files.slack.com\/files-tmb\/T0260V1BR-F0A6V0N9F-2793332b36\/screen_shot_2015-09-04_at_4.26.59_pm_480.png?t=xoxe-2204987399-220009572576-220663233794-4d92389b8a",
            "thumb_480_w": 449,
            "thumb_480_h": 480,
            "thumb_160": "https:\/\/files.slack.com\/files-tmb\/T0260V1BR-F0A6V0N9F-2793332b36\/screen_shot_2015-09-04_at_4.26.59_pm_160.png?t=xoxe-2204987399-220009572576-220663233794-4d92389b8a",
            "image_exif_rotation": 1,
            "original_w": 657,
            "original_h": 703,
            "permalink": "https:\/\/uncorked.slack.com\/files\/chewbacca\/F0A6V0N9F\/screen_shot_2015-09-04_at_4.26.59_pm.png",
            "permalink_public": "https:\/\/slack-files.com\/T0260V1BR-F0A6V0N9F-68542c88ab",
            "channels": [
                "C02LNQWC9"
            ],
            "groups": [],
            "ims": [],
            "comments_count": 0
        },
        "user": "U02F8LF2X",
        "upload": true,
        "display_as_bot": false,
        "username": "chewbacca",
        "bot_id": null,
        "ts": "1441409233.000007"
    },
    {
        "type": "message",
        "user": "U026103R3",
        "text": "that's rad",
        "ts": "1441409243.000008"
    },
    {
        "type": "message",
        "user": "U02F8LF2X",
        "text": "now we can replicate her",
        "ts": "1441409261.000009"
    },
    {
        "type": "message",
        "user": "U026PLK4S",
        "text": "yo!",
        "ts": "1441409276.000010"
    },
    {
        "type": "message",
        "user": "U02918BKW",
        "text": "How are you doing that?",
        "ts": "1441409819.000011"
    },
    {
        "type": "message",
        "user": "U026103R3",
        "text": "i just chatted with josh, he's using the kinect",
        "ts": "1441409837.000012"
    },
    {
        "type": "message",
        "user": "U06LYL84S",
        "text": "no, abby. It's magic",
        "ts": "1441409865.000013"
    },
    {
        "type": "message",
        "user": "U026103R3",
        "text": "oh snap josh lied",
        "ts": "1441409910.000014"
    },
    {
        "type": "message",
        "user": "U02AUNA0P",
        "text": "\/giphy #echo josh is a liar",
        "attachments": [
            {
                "fallback": "giphy: <http:\/\/media1.giphy.com\/gifsu\/26Dq9wp1IrruDIMI8\/giphy-glitter.gif>",
                "image_url": "http:\/\/media1.giphy.com\/gifsu\/26Dq9wp1IrruDIMI8\/giphy-glitter.gif",
                "image_width": 500,
                "image_height": 500,
                "image_bytes": 524605,
                "title": "#echo josh is a liar",
                "id": 1,
                "title_link": "http:\/\/media1.giphy.com\/gifsu\/26Dq9wp1IrruDIMI8\/giphy-glitter.gif"
            }
        ],
        "ts": "1441409954.000015"
    },
    {
        "type": "message",
        "user": "U06LYL84S",
        "text": "For anyone that's curious, this is what we're using",
        "edited": {
            "user": "U06LYL84S",
            "ts": "1441410380.000000"
        },
        "ts": "1441410291.000016"
    },
    {
        "type": "message",
        "user": "U06LYL84S",
        "text": "<https:\/\/msdn.microsoft.com\/en-us\/library\/dn188670.aspx>",
        "ts": "1441410293.000017"
    },
    {
        "type": "message",
        "user": "U02F8LF2X",
        "text": "I don't lie, I trick",
        "ts": "1441411636.000019"
    }
]