[
    {
        "type": "message",
        "user": "U0260V1BX",
        "text": "<!channel> i am going to be WFH after lunch until EOD. I’ll call in for the 3pm wire review but you can find me on slack if you need me.",
        "ts": "1471025316.000123"
    },
    {
        "type": "message",
        "user": "U026E0ZNR",
        "text": "oh yeah, along those lines, I’m gonna try jetting a bit early today to prep for my weekend plans. lemme know if that creates any issues with anyone",
        "ts": "1471026021.000124"
    }
]