[
    {
        "type": "message",
        "user": "U0K8ZSHN0",
        "text": "<https:\/\/twitter.com\/bobby\/status\/859587380902338560>",
        "attachments": [
            {
                "fallback": "<https:\/\/twitter.com\/bobby|@bobby>: i saw one of those startup dog prisons in real life today. <https:\/\/pbs.twimg.com\/media\/C-3eJ8lXcAAjEsq.jpg>",
                "ts": 1493776576,
                "author_name": "bobby",
                "author_link": "https:\/\/twitter.com\/bobby\/status\/859587380902338560",
                "author_icon": "https:\/\/pbs.twimg.com\/profile_images\/630250931452542976\/qZ9l6cSw_normal.jpg",
                "author_subname": "@bobby",
                "text": "i saw one of those startup dog prisons in real life today. <https:\/\/pbs.twimg.com\/media\/C-3eJ8lXcAAjEsq.jpg>",
                "service_name": "twitter",
                "service_url": "https:\/\/twitter.com\/",
                "from_url": "https:\/\/twitter.com\/bobby\/status\/859587380902338560",
                "image_url": "https:\/\/pbs.twimg.com\/media\/C-3eJ8lXcAAjEsq.jpg",
                "image_width": 900,
                "image_height": 1200,
                "image_bytes": 196354,
                "id": 1,
                "footer": "Twitter",
                "footer_icon": "https:\/\/a.slack-edge.com\/6e067\/img\/services\/twitter_pixel_snapped_32.png"
            },
            {
                "text": "<https:\/\/pbs.twimg.com\/media\/C-3eJ8kXYAIZYjX.jpg>",
                "image_url": "https:\/\/pbs.twimg.com\/media\/C-3eJ8kXYAIZYjX.jpg",
                "image_width": 1200,
                "image_height": 900,
                "image_bytes": 106315,
                "id": 2
            }
        ],
        "ts": "1493824906.841328",
        "reactions": [
            {
                "name": "confounded",
                "users": [
                    "U0EL0GLEL"
                ],
                "count": 1
            }
        ]
    },
    {
        "type": "message",
        "user": "U3M4RRNQ5",
        "text": "W T F",
        "ts": "1493825955.188900"
    },
    {
        "type": "message",
        "user": "U3M4RRNQ5",
        "text": "So presumably if someone walks up and unplugs it your dog is left in a sauna",
        "ts": "1493826019.209689",
        "reactions": [
            {
                "name": "scream",
                "users": [
                    "U0260V1BX"
                ],
                "count": 1
            }
        ]
    },
    {
        "type": "message",
        "user": "U026NB2U2",
        "text": "i would hope it would open if you unplugged it, but I'm sure that's in V2.",
        "ts": "1493829820.366189"
    },
    {
        "type": "message",
        "user": "U0K8ZSHN0",
        "text": "so unplug if you want to steal this dog right now! but wait, there's more",
        "ts": "1493834839.843038"
    },
    {
        "type": "message",
        "user": "U026NB2U2",
        "text": "silent dog alarm tripped if you unplug it comes in v3",
        "ts": "1493835949.168496"
    },
    {
        "type": "message",
        "user": "U02F8TTPU",
        "text": "<http:\/\/spectrum.ieee.org\/view-from-the-valley\/energy\/the-smarter-grid\/want-to-know-whats-happening-in-a-building-listen-in-at-the-breaker-box?utm_source=feedburner&amp;utm_medium=feed&amp;utm_campaign=Feed%3A+IeeeSpectrumFullText+%28IEEE+Spectrum+Full+Text%29>",
        "attachments": [
            {
                "service_name": "IEEE Spectrum: Technology, Engineering, and Science News",
                "title": "Want to Know What’s Happening in a Building? Listen in at the Breaker Box, Says Startup Verdigris",
                "title_link": "http:\/\/spectrum.ieee.org\/view-from-the-valley\/energy\/the-smarter-grid\/want-to-know-whats-happening-in-a-building-listen-in-at-the-breaker-box?utm_source=feedburner&utm_medium=feed&utm_campaign=Feed%3A+IeeeSpectrumFullText+%28IEEE+Spectrum+Full+Text%29",
                "text": "Silicon Valley startup Verdigris’ cloud-based analysis can tell whether you’re using a Chromebook or a Mac, or whether a motor is running fine or starting to fail",
                "fallback": "IEEE Spectrum: Technology, Engineering, and Science News: Want to Know What’s Happening in a Building? Listen in at the Breaker Box, Says Startup Verdigris",
                "image_url": "http:\/\/spectrum.ieee.org\/image\/Mjg5NTMwMw.jpeg",
                "from_url": "http:\/\/spectrum.ieee.org\/view-from-the-valley\/energy\/the-smarter-grid\/want-to-know-whats-happening-in-a-building-listen-in-at-the-breaker-box?utm_source=feedburner&utm_medium=feed&utm_campaign=Feed%3A+IeeeSpectrumFullText+%28IEEE+Spectrum+Full+Text%29",
                "image_width": 333,
                "image_height": 250,
                "image_bytes": 45467,
                "service_icon": "http:\/\/spectrum.ieee.org\/favicon.png",
                "id": 1
            }
        ],
        "ts": "1493862936.351467"
    }
]