[
    {
        "type": "message",
        "user": "U02F8LF2X",
        "text": "could I get 47 again today?",
        "ts": "1457636032.000073"
    },
    {
        "type": "message",
        "user": "U02918BKW",
        "text": "yes",
        "ts": "1457636854.000074"
    },
    {
        "type": "message",
        "user": "U02F8LF2X",
        "text": "thanks",
        "ts": "1457636919.000075"
    },
    {
        "type": "message",
        "user": "U026NB2U2",
        "text": "any spots available?",
        "ts": "1457654807.000076"
    },
    {
        "type": "message",
        "user": "U026103R3",
        "text": "<@U02918BKW>: or <@U027PV4AP>  ^",
        "ts": "1457654891.000077"
    },
    {
        "type": "message",
        "user": "U027PV4AP",
        "text": "cage is free.",
        "ts": "1457654916.000078"
    },
    {
        "type": "message",
        "user": "U02918BKW",
        "text": "Looks like most should be, unless adi?",
        "ts": "1457654919.000079"
    },
    {
        "type": "message",
        "user": "U027PV4AP",
        "text": "Marce is taking space 50",
        "ts": "1457654939.000080"
    },
    {
        "type": "message",
        "user": "U02F8LF2X",
        "text": "I left for day. at adx. so 47 available again",
        "ts": "1457656943.000081"
    },
    {
        "type": "message",
        "user": "U0ML49XU0",
        "text": "Forgot parking pass at office. Anyone have a spot I could grab starting at 8am?  Can move later in day if necessary ",
        "ts": "1457663734.000082"
    },
    {
        "type": "message",
        "user": "U026103R3",
        "text": "<@U027PV4AP>: or <@U02918BKW> ^ ",
        "ts": "1457665250.000083"
    },
    {
        "type": "message",
        "user": "U02918BKW",
        "text": "Taylor lot, 2nd on right (cage), it's marked",
        "ts": "1457665722.000084"
    }
]