[
    {
        "user": "U0B9N0HF0",
        "type": "message",
        "subtype": "channel_join",
        "text": "<@U0B9N0HF0|rob> has joined the channel",
        "ts": "1443136868.000002"
    },
    {
        "type": "message",
        "user": "U0261PCRQ",
        "text": "Little Friday in 7 minutes! Grab a beer and bring a pen! ( I will have a few extras, but not enough for everyone)",
        "ts": "1443137044.000003"
    },
    {
        "type": "message",
        "user": "U0261PCRQ",
        "text": "I take back the part about bringing a beer, just get over here!",
        "ts": "1443137457.000004"
    }
]