[
    {
        "type": "message",
        "subtype": "file_share",
        "text": "<@U0260V1BX|melissa> uploaded a file: <https:\/\/uncorked.slack.com\/files\/melissa\/F0E1SN68J\/screen_shot_2015-11-06_at_10.54.00_am.png|Screen Shot 2015-11-06 at 10.54.00 AM.png> and commented: we should maybe update the agenda and remove mary and danielle :confused:",
        "file": {
            "id": "F0E1SN68J",
            "created": 1446836074,
            "timestamp": 1446836074,
            "name": "Screen Shot 2015-11-06 at 10.54.00 AM.png",
            "title": "Screen Shot 2015-11-06 at 10.54.00 AM.png",
            "mimetype": "image\/png",
            "filetype": "png",
            "pretty_type": "PNG",
            "user": "U0260V1BX",
            "editable": false,
            "size": 30007,
            "mode": "hosted",
            "is_external": false,
            "external_type": "",
            "is_public": true,
            "public_url_shared": false,
            "display_as_bot": false,
            "username": "",
            "url_private": "https:\/\/files.slack.com\/files-pri\/T0260V1BR-F0E1SN68J\/screen_shot_2015-11-06_at_10.54.00_am.png?t=xoxe-2204987399-220009572576-220663233794-4d92389b8a",
            "url_private_download": "https:\/\/files.slack.com\/files-pri\/T0260V1BR-F0E1SN68J\/download\/screen_shot_2015-11-06_at_10.54.00_am.png?t=xoxe-2204987399-220009572576-220663233794-4d92389b8a",
            "thumb_64": "https:\/\/files.slack.com\/files-tmb\/T0260V1BR-F0E1SN68J-967d3dd287\/screen_shot_2015-11-06_at_10.54.00_am_64.png?t=xoxe-2204987399-220009572576-220663233794-4d92389b8a",
            "thumb_80": "https:\/\/files.slack.com\/files-tmb\/T0260V1BR-F0E1SN68J-967d3dd287\/screen_shot_2015-11-06_at_10.54.00_am_80.png?t=xoxe-2204987399-220009572576-220663233794-4d92389b8a",
            "thumb_360": "https:\/\/files.slack.com\/files-tmb\/T0260V1BR-F0E1SN68J-967d3dd287\/screen_shot_2015-11-06_at_10.54.00_am_360.png?t=xoxe-2204987399-220009572576-220663233794-4d92389b8a",
            "thumb_360_w": 344,
            "thumb_360_h": 128,
            "thumb_160": "https:\/\/files.slack.com\/files-tmb\/T0260V1BR-F0E1SN68J-967d3dd287\/screen_shot_2015-11-06_at_10.54.00_am_160.png?t=xoxe-2204987399-220009572576-220663233794-4d92389b8a",
            "image_exif_rotation": 1,
            "original_w": 344,
            "original_h": 128,
            "permalink": "https:\/\/uncorked.slack.com\/files\/melissa\/F0E1SN68J\/screen_shot_2015-11-06_at_10.54.00_am.png",
            "permalink_public": "https:\/\/slack-files.com\/T0260V1BR-F0E1SN68J-ad55f71987",
            "channels": [
                "C064SHRPS"
            ],
            "groups": [],
            "ims": [],
            "comments_count": 1,
            "initial_comment": {
                "id": "Fc0E1NVBBM",
                "created": 1446836074,
                "timestamp": 1446836074,
                "user": "U0260V1BX",
                "is_intro": true,
                "comment": "we should maybe update the agenda and remove mary and danielle :confused:"
            }
        },
        "user": "U0260V1BX",
        "upload": true,
        "display_as_bot": false,
        "username": "melissa",
        "bot_id": null,
        "ts": "1446836075.000002"
    }
]