[
    {
        "type": "message",
        "user": "U026PT0D7",
        "text": "<@U06K2R98C> <@U026NB2U2> Did you see Patrick's email at 4:45? He's asking if we could fix it today",
        "ts": "1435881901.000002"
    },
    {
        "user": "U06K2R98C",
        "inviter": "U026PT0D7",
        "type": "message",
        "subtype": "channel_join",
        "text": "<@U06K2R98C|grant> has joined the channel",
        "ts": "1435881906.000003"
    },
    {
        "user": "U026NB2U2",
        "inviter": "U026PT0D7",
        "type": "message",
        "subtype": "channel_join",
        "text": "<@U026NB2U2|marcelino> has joined the channel",
        "ts": "1435881907.000004"
    },
    {
        "type": "message",
        "user": "U026PT0D7",
        "text": "I've identified and fixed one bug, so I can push that update, but there's at least one more bug somewhere (I have a hunch it's in the data from Trapit)",
        "ts": "1435881950.000005"
    },
    {
        "type": "message",
        "user": "U06DFL7BP",
        "text": "what’s the issue?",
        "ts": "1435882134.000006"
    },
    {
        "type": "message",
        "user": "U026PT0D7",
        "text": "Oh shoot, wrong channel",
        "ts": "1435882146.000007"
    },
    {
        "type": "message",
        "user": "U026PT0D7",
        "text": "nvm",
        "ts": "1435882150.000008"
    },
    {
        "type": "message",
        "user": "U06DFL7BP",
        "text": "ha np",
        "ts": "1435882156.000009"
    },
    {
        "type": "message",
        "user": "U06DFL7BP",
        "text": "i was like who is patrick! what’s going on!",
        "ts": "1435882162.000010"
    },
    {
        "type": "message",
        "user": "U026PT0D7",
        "text": "yeah, we're going for the trifecta: LEGO-branded posts through Trapit at OMSI",
        "ts": "1435882203.000011"
    },
    {
        "type": "message",
        "user": "U06DFL7BP",
        "text": ":O",
        "ts": "1435882222.000012"
    }
]